README.md
setup.py
nutripy/__init__.py
nutripy/config.py
nutripy/diet.py
nutripy/nutripy.py
nutripy.egg-info/PKG-INFO
nutripy.egg-info/SOURCES.txt
nutripy.egg-info/dependency_links.txt
nutripy.egg-info/requires.txt
nutripy.egg-info/top_level.txt
tests/__init__.py
tests/test_diet.py
tests/test_nutripy.py