Metadata-Version: 2.1
Name: nutripy
Version: 0.7.0
Summary: A Python module for computing calorie requirements for   individuals based on their needs and objectives
Home-page: https://github.com/yfe404/nutripy
Author: Yann Feunteun
Author-email: yann.feunteun@protonmail.com
License: UNKNOWN
Platform: UNKNOWN
Classifier: Programming Language :: Python :: 3
Classifier: License :: OSI Approved :: MIT License
Classifier: Operating System :: OS Independent
Requires-Python: >=3.6
